qbuild
